oarepo_model_builder_rdm/__init__.py
oarepo_model_builder_rdm/builtin_models/__init__.py
oarepo_model_builder_rdm/builtin_models/rdm.json
oarepo_model_builder_rdm/builtin_models/rdm_elements.yaml
oarepo_model_builder_rdm/datatypes/__init__.py
oarepo_model_builder_rdm/datatypes/components/__init__.py
oarepo_model_builder_rdm/datatypes/components/draft_record.py
oarepo_model_builder_rdm/datatypes/components/ext_resource.py
oarepo_model_builder_rdm/datatypes/components/links.py
oarepo_model_builder_rdm/datatypes/components/marshmallow.py
oarepo_model_builder_rdm/datatypes/components/pid.py
oarepo_model_builder_rdm/datatypes/components/record.py
oarepo_model_builder_rdm/datatypes/components/resource.py
oarepo_model_builder_rdm/datatypes/components/search_options.py
oarepo_model_builder_rdm/datatypes/components/service.py
oarepo_model_builder_rdm/datatypes/components/ui_marshmallow.py
oarepo_model_builder_rdm/datatypes/components/utils.py
oarepo_model_builder_rdm/invenio/__init__.py
oarepo_model_builder_rdm/invenio/invenio_rdm_draft_record.py
oarepo_model_builder_rdm/invenio/invenio_rdm_ext.py
oarepo_model_builder_rdm/invenio/invenio_rdm_ext_draft.py
oarepo_model_builder_rdm/invenio/invenio_rdm_record.py
oarepo_model_builder_rdm/invenio/invenio_rdm_record_metadata.py
oarepo_model_builder_rdm/invenio/invenio_rdm_record_search_options.py
oarepo_model_builder_rdm/invenio/templates/__init__.py
oarepo_model_builder_rdm/invenio/templates/rdm_draft_record.py.jinja2
oarepo_model_builder_rdm/invenio/templates/rdm_ext.py.jinja2
oarepo_model_builder_rdm/invenio/templates/rdm_ext_draft.py.jinja2
oarepo_model_builder_rdm/invenio/templates/rdm_record.py.jinja2
oarepo_model_builder_rdm/invenio/templates/rdm_record_metadata.py.jinja2
oarepo_model_builder_rdm/invenio/templates/rdm_record_search_options.py.jinja2
oarepo_model_builder_rdm/tests/__init__.py
oarepo_model_builder_rdm-1.3.1.dist-info/METADATA
oarepo_model_builder_rdm-1.3.1.dist-info/WHEEL
oarepo_model_builder_rdm-1.3.1.dist-info/entry_points.txt
oarepo_model_builder_rdm-1.3.1.dist-info/top_level.txt
oarepo_model_builder_rdm-1.3.1.dist-info/RECORD
