Metadata-Version: 2.4
Name: oarepo-model-builder-rdm
Version: 1.3.1
Requires-Dist: oarepo-model-builder-tests>=4.0.0
Requires-Dist: oarepo-model-builder>=4.0.0
Requires-Dist: oarepo-model-builder-files>=4.0.0
Requires-Dist: oarepo-model-builder-drafts>=1.0.4
Requires-Dist: oarepo-model-builder-drafts-files>=4.0.0
Requires-Dist: oarepo-model-builder-workflows>=1.0.0
